{"elements":[{"type":"relation","id":165620,"tags":{"audio_anouncement":"yes","bicycle":"no","by_night":"no","colour":"#f18e00","evening":"yes","frequence":"frequent","from":"Noailles","interval":"6","interval:evening":"15","interval:saturday":"7","interval:sunday":"15","name":"T1: Noailles -> Les Caillols","name:oc":"T1: Noalhas -> Lei Calhòus","network":"RTM","opening_hours":"Mo-Su 00:00-01:00,07:00-24:00","operator":"Régie des Transports Marseillais","public_transport:version":"2","ref":"T1","route":"tram","service":"urban","source:name:oc":"ieo-bdtopoc","to":"Les Caillols","travel_time":"20 min","type":"route","wheelchair":"yes","wikidata":"Q3238668"}},{"type":"relation","id":2452277,"tags":{"audio_anouncement":"yes","bicycle":"no","by_night":"no","colour":"#f18e00","evening":"yes","frequence":"frequent","from":"Les Caillols","from:oc":"Lei Calhòus","interval":"6","interval:evening":"15","interval:saturday":"7","interval:sunday":"15","name":"T1: Les Caillols -> Noailles","name:oc":"T1 : Lei Calhòus -> Noalhas","network":"RTM","opening_hours":"Mo-Su 00:00-01:00,07:00-24:00","operator":"Régie des Transports Marseillais","public_transport:version":"2","ref":"T1","route":"tram","service":"urban","source:name:oc":"ieo-bdtopoc","to":"Noailles","to:oc":"Noalhas","travel_time":"20 min","type":"route","wheelchair":"yes","wikidata":"Q3238668"}},{"type":"relation","id":6497377,"tags":{"colour":"#ed1c24","frequence":"frequent","from":"Colette Molina - Le Charrel","from:oc":"Coleta Molina - Lo Charrèu","interval":"00:10","name":"Tram T1 : Colette Molina - Le Charrel -> Gare d'Aubagne","name:oc":"Tram T1 : Coleta Molina - Lo Charrèu -> Estacion d'Aubanha","network":"Lignes de l'Agglo","opening_hours":"Mo-Sa 06:00-21:00","operator":"TPE","public_transport:version":"2","ref":"T1","route":"tram","source:name:oc":"ieo-bdtopoc","to":"Gare d'Aubagne","to:oc":"Estacion d'Aubanha","type":"route","was:network":"Lignes de l'Agglo","wikidata":"Q110618690"}},{"type":"relation","id":6497378,"tags":{"colour":"#ed1c24","frequence":"frequent","from":"Gare d'Aubagne","from:oc":"Estacion d'Aubanha","interval":"00:10","name":"Tram T1 : Gare d'Aubagne -> Colette Molina - Le Charrel","name:oc":"Tram T1 : Estacion d'Aubanha -> Coleta Molina - Lo Charrèu","network":"Lignes de l'Agglo","opening_hours":"Mo-Sa 06:00-21:00","operator":"TPE","public_transport:version":"2","ref":"T1","route":"tram","source:name:oc":"ieo-bdtopoc","to":"Colette Molina - Le Charrel","to:oc":"Coleta Molina - Lo Charrèu","type":"route","was:network":"Lignes de l'Agglo","wikidata":"Q110618690"}},{"type":"relation","id":19937258,"tags":{"construction_start":"2023-11","electrified":"contact_line","gauge":"1435","name":"Val'Tram Aubagne - La Bouilladisse","network":"Lignes de l'Agglo","network:wikidata":"Q3537052","planned:construction_end":"2026","planned:opening_date":"2027","planned:operator":"TPE","route":"tram","type":"route","voltage":"750","wikidata":"Q110618690","ref":"Val'Tram Aubagne - La Bouilladisse"}}]}