{"id":"eu-fra-marseille","file":"systems/europe/france/eu-fra-marseille.geojson","city":"Marseille","country":"France","cityZh":"馬賽","countryZh":"法國","continent":"europe","line_count":2,"station_count":29,"tilt":-22.76,"canRotate":true,"W":200,"H":150,"views":{"compact-hc":{"lines":[{"d":"M 134.40 57.57 L 134.40 69.19 L 134.40 80.81 L 134.40 92.43 L 134.40 98.24 L 134.40 104.05 L 134.40 109.86 L 100.00 109.86 L 65.60 109.86 L 65.60 75.00 L 65.60 40.14 L 82.80 40.14 L 100.00 40.14 L 117.20 40.14 L 134.40 40.14 L 145.87 40.14 L 157.33 40.14 L 168.80 40.14","color":"#0075be"},{"d":"M 31.20 22.71 L 31.20 27.07 L 31.20 31.43 L 31.20 35.79 L 31.20 40.14 L 48.40 40.14 L 65.60 40.14 L 82.80 48.86 L 100.00 57.57 L 134.40 109.86 L 134.40 115.67 L 134.40 121.48 L 134.40 127.29","color":"#e30513"}],"hl":[],"dots":[{"x":134.4,"y":109.9,"fill":"#e11d48"},{"x":134.4,"y":121.5,"fill":"#ffffff"},{"x":134.4,"y":115.7,"fill":"#ffffff"},{"x":168.8,"y":40.1,"fill":"#2563eb"},{"x":31.2,"y":31.4,"fill":"#ffffff"},{"x":31.2,"y":27.1,"fill":"#ffffff"},{"x":31.2,"y":40.1,"fill":"#ec4899"},{"x":48.4,"y":40.1,"fill":"#ffffff"},{"x":100,"y":57.6,"fill":"#a855f7"},{"x":82.8,"y":48.9,"fill":"#ffffff"},{"x":157.3,"y":40.1,"fill":"#ffffff"},{"x":145.9,"y":40.1,"fill":"#ffffff"},{"x":134.4,"y":40.1,"fill":"#9ca3af"},{"x":117.2,"y":40.1,"fill":"#ffffff"},{"x":100,"y":40.1,"fill":"#ffffff"},{"x":65.6,"y":75,"fill":"#ec4899"},{"x":65.6,"y":109.9,"fill":"#a855f7"},{"x":134.4,"y":104,"fill":"#ffffff"},{"x":134.4,"y":98.2,"fill":"#ffffff"},{"x":134.4,"y":57.6,"fill":"#2563eb"},{"x":134.4,"y":80.8,"fill":"#ffffff"},{"x":134.4,"y":92.4,"fill":"#9ca3af"},{"x":134.4,"y":69.2,"fill":"#ffffff"},{"x":31.2,"y":35.8,"fill":"#ffffff"},{"x":100,"y":109.9,"fill":"#ffffff"},{"x":65.6,"y":40.1,"fill":"#e11d48"},{"x":134.4,"y":127.3,"fill":"#2563eb"},{"x":82.8,"y":40.1,"fill":"#ffffff"},{"x":31.2,"y":22.7,"fill":"#2563eb"}],"grid":{"xs":[14,48.4,82.8,117.2,151.6,186],"ys":[14,31.4,48.9,66.3,83.7,101.1,118.6,136]}},"rwd-hc":{"lines":[{"d":"M 134.40 109.86 L 65.60 109.86","color":"#0075be"},{"d":"M 65.60 40.14 L 134.40 40.14","color":"#0075be"},{"d":"M 134.40 109.86 L 100.00 75.46 L 100.00 57.57","color":"#e30513"},{"d":"M 100.00 57.57 L 83.03 57.57 L 65.60 40.14","color":"#e30513"},{"d":"M 65.60 75.00 L 65.60 40.14","color":"#0075be"},{"d":"M 134.40 57.57 L 134.40 92.43","color":"#0075be"},{"d":"M 65.60 109.86 L 65.60 75.00","color":"#0075be"},{"d":"M 134.40 40.14 L 168.80 40.14","color":"#0075be"},{"d":"M 65.60 40.14 L 31.20 40.14","color":"#e30513"},{"d":"M 134.40 92.43 L 134.40 109.86","color":"#0075be"},{"d":"M 134.40 109.86 L 134.40 127.29","color":"#e30513"},{"d":"M 31.20 40.14 L 31.20 22.71","color":"#e30513"}],"hl":[{"d":"M 134.40 109.86 L 65.60 109.86","color":"#2563eb"},{"d":"M 134.40 109.86 L 100.00 75.46 L 100.00 57.57","color":"#2563eb"},{"d":"M 100.00 57.57 L 83.03 57.57 L 65.60 40.14","color":"#2563eb"},{"d":"M 65.60 75.00 L 65.60 40.14","color":"#2563eb"},{"d":"M 65.60 109.86 L 65.60 75.00","color":"#2563eb"}],"dots":[{"x":134.4,"y":109.9,"fill":"#e11d48"},{"x":134.4,"y":121.5,"fill":"#ffffff"},{"x":134.4,"y":115.7,"fill":"#ffffff"},{"x":168.8,"y":40.1,"fill":"#2563eb"},{"x":31.2,"y":31.4,"fill":"#ffffff"},{"x":31.2,"y":27.1,"fill":"#ffffff"},{"x":31.2,"y":40.1,"fill":"#ec4899"},{"x":48.4,"y":40.1,"fill":"#ffffff"},{"x":100,"y":57.6,"fill":"#a855f7"},{"x":80.3,"y":54.9,"fill":"#ffffff"},{"x":157.3,"y":40.1,"fill":"#ffffff"},{"x":145.9,"y":40.1,"fill":"#ffffff"},{"x":134.4,"y":40.1,"fill":"#9ca3af"},{"x":117.2,"y":40.1,"fill":"#ffffff"},{"x":100,"y":40.1,"fill":"#ffffff"},{"x":65.6,"y":75,"fill":"#ec4899"},{"x":65.6,"y":109.9,"fill":"#a855f7"},{"x":134.4,"y":104,"fill":"#ffffff"},{"x":134.4,"y":98.2,"fill":"#ffffff"},{"x":134.4,"y":57.6,"fill":"#2563eb"},{"x":134.4,"y":80.8,"fill":"#ffffff"},{"x":134.4,"y":92.4,"fill":"#9ca3af"},{"x":134.4,"y":69.2,"fill":"#ffffff"},{"x":31.2,"y":35.8,"fill":"#ffffff"},{"x":100,"y":109.9,"fill":"#ffffff"},{"x":65.6,"y":40.1,"fill":"#e11d48"},{"x":134.4,"y":127.3,"fill":"#2563eb"},{"x":82.8,"y":40.1,"fill":"#ffffff"},{"x":31.2,"y":22.7,"fill":"#2563eb"}],"grid":{"xs":[14,48.4,82.8,117.2,151.6,186],"ys":[14,31.4,48.9,66.3,83.7,101.1,118.6,136]}},"compact-rect":{"lines":[{"d":"M 173.71 75.00 L 165.52 80.81 L 157.33 86.62 L 149.14 92.43 L 140.95 98.24 L 132.76 104.05 L 124.57 109.86 L 100.00 109.86 L 75.43 109.86 L 75.43 92.43 L 75.43 75.00 L 87.71 70.64 L 100.00 66.29 L 112.29 61.93 L 124.57 57.57 L 132.76 51.76 L 140.95 45.95 L 149.14 40.14","color":"#0075be"},{"d":"M 26.29 22.71 L 32.43 27.07 L 38.57 31.43 L 44.71 35.79 L 50.86 40.14 L 63.14 57.57 L 75.43 75.00 L 87.71 83.71 L 100.00 92.43 L 124.57 109.86 L 124.57 115.67 L 124.57 121.48 L 124.57 127.29","color":"#e30513"}],"hl":[],"dots":[{"x":124.6,"y":109.9,"fill":"#e11d48"},{"x":124.6,"y":121.5,"fill":"#ffffff"},{"x":124.6,"y":115.7,"fill":"#ffffff"},{"x":149.1,"y":40.1,"fill":"#2563eb"},{"x":38.6,"y":31.4,"fill":"#ffffff"},{"x":32.4,"y":27.1,"fill":"#ffffff"},{"x":50.9,"y":40.1,"fill":"#ec4899"},{"x":63.1,"y":57.6,"fill":"#ffffff"},{"x":100,"y":92.4,"fill":"#a855f7"},{"x":87.7,"y":83.7,"fill":"#ffffff"},{"x":141,"y":46,"fill":"#ffffff"},{"x":132.8,"y":51.8,"fill":"#ffffff"},{"x":124.6,"y":57.6,"fill":"#9ca3af"},{"x":112.3,"y":61.9,"fill":"#ffffff"},{"x":100,"y":66.3,"fill":"#ffffff"},{"x":75.4,"y":92.4,"fill":"#ec4899"},{"x":75.4,"y":109.9,"fill":"#a855f7"},{"x":132.8,"y":104,"fill":"#ffffff"},{"x":141,"y":98.2,"fill":"#ffffff"},{"x":173.7,"y":75,"fill":"#2563eb"},{"x":157.3,"y":86.6,"fill":"#ffffff"},{"x":149.1,"y":92.4,"fill":"#9ca3af"},{"x":165.5,"y":80.8,"fill":"#ffffff"},{"x":44.7,"y":35.8,"fill":"#ffffff"},{"x":100,"y":109.9,"fill":"#ffffff"},{"x":75.4,"y":75,"fill":"#e11d48"},{"x":124.6,"y":127.3,"fill":"#2563eb"},{"x":87.7,"y":70.6,"fill":"#ffffff"},{"x":26.3,"y":22.7,"fill":"#2563eb"}],"grid":{"xs":[14,38.6,63.1,87.7,112.3,136.9,161.4,186],"ys":[14,31.4,48.9,66.3,83.7,101.1,118.6,136]}},"rwd-rect":{"lines":[{"d":"M 75.43 75.00 L 92.86 57.57 L 124.57 57.57","color":"#0075be"},{"d":"M 124.57 109.86 L 75.43 109.86","color":"#0075be"},{"d":"M 75.43 75.00 L 50.86 50.43 L 50.86 40.14","color":"#e30513"},{"d":"M 124.57 109.86 L 107.14 92.43 L 100.00 92.43","color":"#e30513"},{"d":"M 173.71 75.00 L 166.57 75.00 L 149.14 92.43","color":"#0075be"},{"d":"M 50.86 40.14 L 33.43 22.71 L 26.29 22.71","color":"#e30513"},{"d":"M 100.00 92.43 L 82.57 75.00 L 75.43 75.00","color":"#e30513"},{"d":"M 149.14 92.43 L 131.71 109.86 L 124.57 109.86","color":"#0075be"},{"d":"M 124.57 57.57 L 131.71 57.57 L 149.14 40.14","color":"#0075be"},{"d":"M 75.43 109.86 L 75.43 92.43","color":"#0075be"},{"d":"M 124.57 109.86 L 124.57 127.29","color":"#e30513"},{"d":"M 75.43 92.43 L 75.43 75.00","color":"#0075be"}],"hl":[{"d":"M 124.57 109.86 L 75.43 109.86","color":"#2563eb"},{"d":"M 124.57 109.86 L 107.14 92.43 L 100.00 92.43","color":"#2563eb"},{"d":"M 100.00 92.43 L 82.57 75.00 L 75.43 75.00","color":"#2563eb"},{"d":"M 75.43 109.86 L 75.43 92.43","color":"#2563eb"},{"d":"M 75.43 92.43 L 75.43 75.00","color":"#2563eb"}],"dots":[{"x":124.6,"y":109.9,"fill":"#e11d48"},{"x":124.6,"y":121.5,"fill":"#ffffff"},{"x":124.6,"y":115.7,"fill":"#ffffff"},{"x":149.1,"y":40.1,"fill":"#2563eb"},{"x":39.6,"y":28.9,"fill":"#ffffff"},{"x":34,"y":23.3,"fill":"#ffffff"},{"x":50.9,"y":40.1,"fill":"#ec4899"},{"x":59.5,"y":59.1,"fill":"#ffffff"},{"x":100,"y":92.4,"fill":"#a855f7"},{"x":88.8,"y":81.2,"fill":"#ffffff"},{"x":141.6,"y":47.6,"fill":"#ffffff"},{"x":134.2,"y":55.1,"fill":"#ffffff"},{"x":124.6,"y":57.6,"fill":"#9ca3af"},{"x":110.5,"y":57.6,"fill":"#ffffff"},{"x":96.4,"y":57.6,"fill":"#ffffff"},{"x":75.4,"y":92.4,"fill":"#ec4899"},{"x":75.4,"y":109.9,"fill":"#a855f7"},{"x":134.2,"y":107.4,"fill":"#ffffff"},{"x":141.6,"y":99.9,"fill":"#ffffff"},{"x":173.7,"y":75,"fill":"#2563eb"},{"x":156.6,"y":84.9,"fill":"#ffffff"},{"x":149.1,"y":92.4,"fill":"#9ca3af"},{"x":164.1,"y":77.4,"fill":"#ffffff"},{"x":45.2,"y":34.5,"fill":"#ffffff"},{"x":100,"y":109.9,"fill":"#ffffff"},{"x":75.4,"y":75,"fill":"#e11d48"},{"x":124.6,"y":127.3,"fill":"#2563eb"},{"x":85.4,"y":65,"fill":"#ffffff"},{"x":26.3,"y":22.7,"fill":"#2563eb"}],"grid":{"xs":[14,38.6,63.1,87.7,112.3,136.9,161.4,186],"ys":[14,31.4,48.9,66.3,83.7,101.1,118.6,136]}},"compact-align":{"lines":[{"d":"M 173.71 57.57 L 165.52 69.19 L 157.33 80.81 L 149.14 92.43 L 140.95 98.24 L 132.76 104.05 L 124.57 109.86 L 100.00 101.14 L 75.43 92.43 L 75.43 75.00 L 75.43 40.14 L 93.86 40.14 L 112.29 40.14 L 130.71 40.14 L 149.14 40.14 L 157.33 40.14 L 165.52 40.14 L 173.71 40.14","color":"#0075be"},{"d":"M 26.29 22.71 L 32.43 27.07 L 38.57 31.43 L 44.71 35.79 L 50.86 40.14 L 63.14 40.14 L 75.43 40.14 L 87.71 66.29 L 100.00 92.43 L 124.57 109.86 L 132.76 115.67 L 140.95 121.48 L 149.14 127.29","color":"#e30513"}],"hl":[],"dots":[{"x":124.6,"y":109.9,"fill":"#e11d48"},{"x":141,"y":121.5,"fill":"#ffffff"},{"x":132.8,"y":115.7,"fill":"#ffffff"},{"x":173.7,"y":40.1,"fill":"#2563eb"},{"x":38.6,"y":31.4,"fill":"#ffffff"},{"x":32.4,"y":27.1,"fill":"#ffffff"},{"x":50.9,"y":40.1,"fill":"#ec4899"},{"x":63.1,"y":40.1,"fill":"#ffffff"},{"x":100,"y":92.4,"fill":"#a855f7"},{"x":87.7,"y":66.3,"fill":"#ffffff"},{"x":165.5,"y":40.1,"fill":"#ffffff"},{"x":157.3,"y":40.1,"fill":"#ffffff"},{"x":149.1,"y":40.1,"fill":"#9ca3af"},{"x":130.7,"y":40.1,"fill":"#ffffff"},{"x":112.3,"y":40.1,"fill":"#ffffff"},{"x":75.4,"y":75,"fill":"#ec4899"},{"x":75.4,"y":92.4,"fill":"#a855f7"},{"x":132.8,"y":104,"fill":"#ffffff"},{"x":141,"y":98.2,"fill":"#ffffff"},{"x":173.7,"y":57.6,"fill":"#2563eb"},{"x":157.3,"y":80.8,"fill":"#ffffff"},{"x":149.1,"y":92.4,"fill":"#9ca3af"},{"x":165.5,"y":69.2,"fill":"#ffffff"},{"x":44.7,"y":35.8,"fill":"#ffffff"},{"x":100,"y":101.1,"fill":"#ffffff"},{"x":75.4,"y":40.1,"fill":"#e11d48"},{"x":149.1,"y":127.3,"fill":"#2563eb"},{"x":93.9,"y":40.1,"fill":"#ffffff"},{"x":26.3,"y":22.7,"fill":"#2563eb"}],"grid":{"xs":[14,38.6,63.1,87.7,112.3,136.9,161.4,186],"ys":[14,31.4,48.9,66.3,83.7,101.1,118.6,136]}},"rwd-align":{"lines":[{"d":"M 75.43 40.14 L 149.14 40.14","color":"#0075be"},{"d":"M 100.00 92.43 L 100.00 64.71 L 75.43 40.14","color":"#e30513"},{"d":"M 124.57 109.86 L 92.86 109.86 L 75.43 92.43","color":"#0075be"},{"d":"M 173.71 57.57 L 173.71 67.86 L 149.14 92.43","color":"#0075be"},{"d":"M 75.43 75.00 L 75.43 40.14","color":"#0075be"},{"d":"M 124.57 109.86 L 107.14 92.43 L 100.00 92.43","color":"#e30513"},{"d":"M 50.86 40.14 L 43.71 40.14 L 26.29 22.71","color":"#e30513"},{"d":"M 149.14 92.43 L 131.71 109.86 L 124.57 109.86","color":"#0075be"},{"d":"M 124.57 109.86 L 142.00 127.29 L 149.14 127.29","color":"#e30513"},{"d":"M 149.14 40.14 L 173.71 40.14","color":"#0075be"},{"d":"M 75.43 40.14 L 50.86 40.14","color":"#e30513"},{"d":"M 75.43 92.43 L 75.43 75.00","color":"#0075be"}],"hl":[{"d":"M 100.00 92.43 L 100.00 64.71 L 75.43 40.14","color":"#2563eb"},{"d":"M 124.57 109.86 L 92.86 109.86 L 75.43 92.43","color":"#2563eb"},{"d":"M 75.43 75.00 L 75.43 40.14","color":"#2563eb"},{"d":"M 124.57 109.86 L 107.14 92.43 L 100.00 92.43","color":"#2563eb"},{"d":"M 75.43 92.43 L 75.43 75.00","color":"#2563eb"}],"dots":[{"x":124.6,"y":109.9,"fill":"#e11d48"},{"x":139.6,"y":124.8,"fill":"#ffffff"},{"x":132.1,"y":117.4,"fill":"#ffffff"},{"x":173.7,"y":40.1,"fill":"#2563eb"},{"x":37.5,"y":34,"fill":"#ffffff"},{"x":31.9,"y":28.3,"fill":"#ffffff"},{"x":50.9,"y":40.1,"fill":"#ec4899"},{"x":63.1,"y":40.1,"fill":"#ffffff"},{"x":100,"y":92.4,"fill":"#a855f7"},{"x":97.5,"y":62.2,"fill":"#ffffff"},{"x":165.5,"y":40.1,"fill":"#ffffff"},{"x":157.3,"y":40.1,"fill":"#ffffff"},{"x":149.1,"y":40.1,"fill":"#9ca3af"},{"x":130.7,"y":40.1,"fill":"#ffffff"},{"x":112.3,"y":40.1,"fill":"#ffffff"},{"x":75.4,"y":75,"fill":"#ec4899"},{"x":75.4,"y":92.4,"fill":"#a855f7"},{"x":134.2,"y":107.4,"fill":"#ffffff"},{"x":141.6,"y":99.9,"fill":"#ffffff"},{"x":173.7,"y":57.6,"fill":"#2563eb"},{"x":159.8,"y":81.8,"fill":"#ffffff"},{"x":149.1,"y":92.4,"fill":"#9ca3af"},{"x":170.4,"y":71.2,"fill":"#ffffff"},{"x":43.1,"y":39.6,"fill":"#ffffff"},{"x":96.4,"y":109.9,"fill":"#ffffff"},{"x":75.4,"y":40.1,"fill":"#e11d48"},{"x":149.1,"y":127.3,"fill":"#2563eb"},{"x":93.9,"y":40.1,"fill":"#ffffff"},{"x":26.3,"y":22.7,"fill":"#2563eb"}],"grid":{"xs":[14,38.6,63.1,87.7,112.3,136.9,161.4,186],"ys":[14,31.4,48.9,66.3,83.7,101.1,118.6,136]}},"compact-ilp":{"lines":[{"d":"M 173.71 57.57 L 165.52 69.19 L 157.33 80.81 L 149.14 92.43 L 140.95 98.24 L 132.76 104.05 L 124.57 109.86 L 100.00 101.14 L 75.43 92.43 L 75.43 75.00 L 75.43 40.14 L 93.86 40.14 L 112.29 40.14 L 130.71 40.14 L 149.14 40.14 L 157.33 40.14 L 165.52 40.14 L 173.71 40.14","color":"#0075be"},{"d":"M 26.29 22.71 L 32.43 27.07 L 38.57 31.43 L 44.71 35.79 L 50.86 40.14 L 63.14 40.14 L 75.43 40.14 L 87.71 66.29 L 100.00 92.43 L 124.57 109.86 L 132.76 115.67 L 140.95 121.48 L 149.14 127.29","color":"#e30513"}],"hl":[],"dots":[{"x":124.6,"y":109.9,"fill":"#e11d48"},{"x":141,"y":121.5,"fill":"#ffffff"},{"x":132.8,"y":115.7,"fill":"#ffffff"},{"x":173.7,"y":40.1,"fill":"#2563eb"},{"x":38.6,"y":31.4,"fill":"#ffffff"},{"x":32.4,"y":27.1,"fill":"#ffffff"},{"x":50.9,"y":40.1,"fill":"#ec4899"},{"x":63.1,"y":40.1,"fill":"#ffffff"},{"x":100,"y":92.4,"fill":"#a855f7"},{"x":87.7,"y":66.3,"fill":"#ffffff"},{"x":165.5,"y":40.1,"fill":"#ffffff"},{"x":157.3,"y":40.1,"fill":"#ffffff"},{"x":149.1,"y":40.1,"fill":"#9ca3af"},{"x":130.7,"y":40.1,"fill":"#ffffff"},{"x":112.3,"y":40.1,"fill":"#ffffff"},{"x":75.4,"y":75,"fill":"#ec4899"},{"x":75.4,"y":92.4,"fill":"#a855f7"},{"x":132.8,"y":104,"fill":"#ffffff"},{"x":141,"y":98.2,"fill":"#ffffff"},{"x":173.7,"y":57.6,"fill":"#2563eb"},{"x":157.3,"y":80.8,"fill":"#ffffff"},{"x":149.1,"y":92.4,"fill":"#9ca3af"},{"x":165.5,"y":69.2,"fill":"#ffffff"},{"x":44.7,"y":35.8,"fill":"#ffffff"},{"x":100,"y":101.1,"fill":"#ffffff"},{"x":75.4,"y":40.1,"fill":"#e11d48"},{"x":149.1,"y":127.3,"fill":"#2563eb"},{"x":93.9,"y":40.1,"fill":"#ffffff"},{"x":26.3,"y":22.7,"fill":"#2563eb"}],"grid":{"xs":[14,38.6,63.1,87.7,112.3,136.9,161.4,186],"ys":[14,31.4,48.9,66.3,83.7,101.1,118.6,136]}},"rwd-ilp":{"lines":[{"d":"M 75.43 40.14 L 149.14 40.14","color":"#0075be"},{"d":"M 100.00 92.43 L 100.00 64.71 L 75.43 40.14","color":"#e30513"},{"d":"M 124.57 109.86 L 92.86 109.86 L 75.43 92.43","color":"#0075be"},{"d":"M 173.71 57.57 L 173.71 67.86 L 149.14 92.43","color":"#0075be"},{"d":"M 75.43 75.00 L 75.43 40.14","color":"#0075be"},{"d":"M 124.57 109.86 L 107.14 92.43 L 100.00 92.43","color":"#e30513"},{"d":"M 50.86 40.14 L 43.71 40.14 L 26.29 22.71","color":"#e30513"},{"d":"M 149.14 92.43 L 131.71 109.86 L 124.57 109.86","color":"#0075be"},{"d":"M 124.57 109.86 L 142.00 127.29 L 149.14 127.29","color":"#e30513"},{"d":"M 149.14 40.14 L 173.71 40.14","color":"#0075be"},{"d":"M 75.43 40.14 L 50.86 40.14","color":"#e30513"},{"d":"M 75.43 92.43 L 75.43 75.00","color":"#0075be"}],"hl":[{"d":"M 100.00 92.43 L 100.00 64.71 L 75.43 40.14","color":"#2563eb"},{"d":"M 124.57 109.86 L 92.86 109.86 L 75.43 92.43","color":"#2563eb"},{"d":"M 75.43 75.00 L 75.43 40.14","color":"#2563eb"},{"d":"M 124.57 109.86 L 107.14 92.43 L 100.00 92.43","color":"#2563eb"},{"d":"M 75.43 92.43 L 75.43 75.00","color":"#2563eb"}],"dots":[{"x":124.6,"y":109.9,"fill":"#e11d48"},{"x":139.6,"y":124.8,"fill":"#ffffff"},{"x":132.1,"y":117.4,"fill":"#ffffff"},{"x":173.7,"y":40.1,"fill":"#2563eb"},{"x":37.5,"y":34,"fill":"#ffffff"},{"x":31.9,"y":28.3,"fill":"#ffffff"},{"x":50.9,"y":40.1,"fill":"#ec4899"},{"x":63.1,"y":40.1,"fill":"#ffffff"},{"x":100,"y":92.4,"fill":"#a855f7"},{"x":97.5,"y":62.2,"fill":"#ffffff"},{"x":165.5,"y":40.1,"fill":"#ffffff"},{"x":157.3,"y":40.1,"fill":"#ffffff"},{"x":149.1,"y":40.1,"fill":"#9ca3af"},{"x":130.7,"y":40.1,"fill":"#ffffff"},{"x":112.3,"y":40.1,"fill":"#ffffff"},{"x":75.4,"y":75,"fill":"#ec4899"},{"x":75.4,"y":92.4,"fill":"#a855f7"},{"x":134.2,"y":107.4,"fill":"#ffffff"},{"x":141.6,"y":99.9,"fill":"#ffffff"},{"x":173.7,"y":57.6,"fill":"#2563eb"},{"x":159.8,"y":81.8,"fill":"#ffffff"},{"x":149.1,"y":92.4,"fill":"#9ca3af"},{"x":170.4,"y":71.2,"fill":"#ffffff"},{"x":43.1,"y":39.6,"fill":"#ffffff"},{"x":96.4,"y":109.9,"fill":"#ffffff"},{"x":75.4,"y":40.1,"fill":"#e11d48"},{"x":149.1,"y":127.3,"fill":"#2563eb"},{"x":93.9,"y":40.1,"fill":"#ffffff"},{"x":26.3,"y":22.7,"fill":"#2563eb"}],"grid":{"xs":[14,38.6,63.1,87.7,112.3,136.9,161.4,186],"ys":[14,31.4,48.9,66.3,83.7,101.1,118.6,136]}}},"_fp":"8:7s2g3z"}